adaptive/__init__.py
adaptive/adaptive.py
adaptive/exceptions/__init__.py
adaptive/exceptions/api.py
adaptive/models/completions/__init__.py
adaptive/models/completions/anthropic.py
adaptive/models/completions/base.py
adaptive/models/completions/completions.py
adaptive/models/completions/deepseek.py
adaptive/models/completions/groq.py
adaptive/models/completions/openai.py
adaptive/models/completions/types.py
adaptive/resources/__init__.py
adaptive/resources/base.py
adaptive/resources/chat/__init__.py
adaptive/resources/chat/chat.py
adaptive/resources/chat/completions/__init__.py
adaptive/resources/chat/completions/completions.py
adaptive/utils/__init__.py
adaptive/utils/streaming.py
adaptive_ai-0.1.2.dist-info/METADATA
adaptive_ai-0.1.2.dist-info/WHEEL
adaptive_ai-0.1.2.dist-info/entry_points.txt
adaptive_ai-0.1.2.dist-info/RECORD
